DataVisual/__init__.py
DataVisual/_version.py
DataVisual/multi_array.py
DataVisual/tables.py
DataVisual/tools/__init__.py
DataVisual/tools/directories.py
DataVisual/units/__init__.py
DataVisual/units/base_class.py
DataVisual/units/components.py
DataVisual-1.5.0.post0.dist-info/LICENSE
DataVisual-1.5.0.post0.dist-info/METADATA
DataVisual-1.5.0.post0.dist-info/WHEEL
DataVisual-1.5.0.post0.dist-info/top_level.txt
DataVisual-1.5.0.post0.dist-info/RECORD
