Metadata-Version: 2.1
Name: DataVisual
Version: 1.5.0.post0
Summary: A package multidimensional data visualisation.
Author-email: Martin Poinsinet de Sivry-Houle <martin.poinsinet.de.sivry@gmail.com>
License: MIT License
Keywords: data,visualization
Classifier: Programming Language :: Python
Classifier: Programming Language :: Python :: 3
Classifier: Programming Language :: Python :: 3.11
Classifier: Programming Language :: Python :: 3.12
Classifier: Programming Language :: Python :: Implementation :: CPython
Classifier: Development Status :: 4 - Beta
Classifier: Topic :: Scientific/Engineering :: Physics
Classifier: License :: OSI Approved :: MIT License
Classifier: Intended Audience :: Science/Research
Requires-Python: >=3.10
License-File: LICENSE
Requires-Dist: numpy==1.*
Requires-Dist: MPSPlots
Provides-Extra: documentation
Requires-Dist: numpydoc==1.6.0; extra == "documentation"
Requires-Dist: sphinx>=5.1.1; extra == "documentation"
Requires-Dist: sphinx-gallery==0.15.0; extra == "documentation"
Requires-Dist: sphinx-rtd-theme==2.0.0; extra == "documentation"
Requires-Dist: pydata-sphinx-theme==0.14.1; extra == "documentation"
Provides-Extra: testing
Requires-Dist: pytest>=0.6; extra == "testing"
Requires-Dist: pytest-cov>=2.0; extra == "testing"
Requires-Dist: pytest-json-report==1.5.0; extra == "testing"
Requires-Dist: mypy>=0.910; extra == "testing"
Requires-Dist: flake8>=3.9; extra == "testing"
Requires-Dist: tox>=3.24; extra == "testing"
Requires-Dist: coverage==6.5.0; extra == "testing"
